{
  "contacts": [
    {
      "id": "6478",
      "profile": "https://firebasestorage.googleapis.com/v0/b/contact-db-4523d.appspot.com/o/1.jpg?alt=media&token=d45f2d2d-70b3-4d5e-839e-9d8288c0322b",
      "name": "user 1",
      "email": "u1@gmail.com",
      "contactNumber": "1234567888",
      "address": "Address...",
      "notes": "Notes..."
    },
    {
      "id": "0128",
      "profile": "https://firebasestorage.googleapis.com/v0/b/contact-db-4523d.appspot.com/o/6.jpg?alt=media&token=ec5cc4ce-1522-4a41-80fd-8f048d0975c9",
      "name": "user 2",
      "email": "u2@gmail.com",
      "contactNumber": "1234567890",
      "address": "Address...",
      "notes": "Notes..."
    },
    {
      "id": "5398",
      "profile": "https://firebasestorage.googleapis.com/v0/b/contact-db-4523d.appspot.com/o/5.jpg?alt=media&token=c0b6dcc9-df95-4850-b3c4-bf6f1b598f1c",
      "name": "user 3",
      "email": "u3@gmail.com",
      "contactNumber": "1234567890",
      "address": "Address...",
      "notes": "Notes..."
    }
  ]
}